{
  "appInfo" : {
    "build" : "211.7142.45",
    "buildDate" : "2021-04-30T10:16:31.692Z[UTC]",
    "productCode" : "IC",
    "generated" : "2021-06-01T19:22:52.8990826Z",
    "os" : "Windows 10 10.0",
    "runtime" : "Oracle Corporation 15.0.2 15.0.2+7-27"
  },
  "runtimeInfo" : {
    "maxMemory" : 536870912,
    "numberOfProcessors" : 8,
    "maxNumberOfIndexingThreads" : 4,
    "maxSizeOfFileForIntelliSense" : 2560000,
    "maxSizeOfFileForContentLoading" : 20971520
  },
  "projectIndexingHistory" : {
    "projectName" : "untitled",
    "times" : {
      "totalUpdatingTime" : 7248622700,
      "indexingTime" : 93795900,
      "contentLoadingTime" : 3136499,
      "scanFilesTime" : 7086718500,
      "pushPropertiesTime" : 17249000,
      "indexExtensionsTime" : 0,
      "updatingStart" : "2021-06-01T19:22:45.646993Z",
      "updatingEnd" : "2021-06-01T19:22:52.8949816Z",
      "totalSuspendedTime" : 0,
      "wasInterrupted" : false
    },
    "fileCount" : {
      "numberOfFileProviders" : 8,
      "numberOfScannedFiles" : 40944,
      "numberOfFilesIndexedByInfrastructureExtensionsDuringScan" : 0,
      "numberOfFilesScheduledForIndexingAfterScan" : 1,
      "numberOfFilesIndexedByInfrastructureExtensionsDuringIndexingStage" : 1,
      "numberOfFilesIndexedWithLoadingContent" : 1
    },
    "totalStatsPerFileType" : [ {
      "fileType" : "JAVA",
      "partOfTotalProcessingTime" : {
        "part" : 61022900,
        "total" : 61022900
      },
      "partOfTotalContentLoadingTime" : {
        "part" : 2877400,
        "total" : 2877400
      },
      "totalNumberOfFiles" : 1,
      "totalFilesSize" : 59,
      "indexingSpeed" : {
        "totalBytes" : 59,
        "totalTime" : 61022900
      },
      "biggestContributors" : [ {
        "providerName" : "Module 'untitled'",
        "numberOfFiles" : 1,
        "totalFilesSize" : 59,
        "partOfTotalProcessingTimeOfThisFileType" : {
          "part" : 61022900,
          "total" : 61022900
        }
      } ]
    } ],
    "totalStatsPerIndexer" : [ ],
    "scanningStatistics" : [ {
      "providerName" : "JDK 16",
      "numberOfScannedFiles" : 40717,
      "numberOfSkippedFiles" : 0,
      "numberOfFilesForIndexing" : 0,
      "numberOfFilesFullyIndexedByInfrastructureExtensions" : 0,
      "scanningTime" : 4650117800,
      "timeProcessingUpToDateFiles" : 0,
      "timeUpdatingContentLessIndexes" : 235848800,
      "timeIndexingWithoutContent" : 0
    }, {
      "providerName" : "com.intellij.javaee.ExternalResourcesRootsProvider@51fef733",
      "numberOfScannedFiles" : 221,
      "numberOfSkippedFiles" : 4,
      "numberOfFilesForIndexing" : 0,
      "numberOfFilesFullyIndexedByInfrastructureExtensions" : 0,
      "scanningTime" : 1529992800,
      "timeProcessingUpToDateFiles" : 0,
      "timeUpdatingContentLessIndexes" : 6942700,
      "timeIndexingWithoutContent" : 0
    }, {
      "providerName" : "Module 'untitled'",
      "numberOfScannedFiles" : 6,
      "numberOfSkippedFiles" : 0,
      "numberOfFilesForIndexing" : 1,
      "numberOfFilesFullyIndexedByInfrastructureExtensions" : 0,
      "scanningTime" : 260941700,
      "timeProcessingUpToDateFiles" : 0,
      "timeUpdatingContentLessIndexes" : 655600,
      "timeIndexingWithoutContent" : 1250800
    }, {
      "providerName" : "com.intellij.ide.scratch.ScratchesAndConsolesIndexSetContributor@4debe5a2",
      "numberOfScannedFiles" : 0,
      "numberOfSkippedFiles" : 0,
      "numberOfFilesForIndexing" : 0,
      "numberOfFilesFullyIndexedByInfrastructureExtensions" : 0,
      "scanningTime" : 0,
      "timeProcessingUpToDateFiles" : 0,
      "timeUpdatingContentLessIndexes" : 0,
      "timeIndexingWithoutContent" : 0
    }, {
      "providerName" : "com.intellij.javaee.ExternalResourcesRootsProvider@51fef733",
      "numberOfScannedFiles" : 0,
      "numberOfSkippedFiles" : 0,
      "numberOfFilesForIndexing" : 0,
      "numberOfFilesFullyIndexedByInfrastructureExtensions" : 0,
      "scanningTime" : 0,
      "timeProcessingUpToDateFiles" : 0,
      "timeUpdatingContentLessIndexes" : 0,
      "timeIndexingWithoutContent" : 0
    }, {
      "providerName" : "com.intellij.ide.scratch.ScratchesAndConsolesIndexSetContributor@4debe5a2",
      "numberOfScannedFiles" : 0,
      "numberOfSkippedFiles" : 0,
      "numberOfFilesForIndexing" : 0,
      "numberOfFilesFullyIndexedByInfrastructureExtensions" : 0,
      "scanningTime" : 0,
      "timeProcessingUpToDateFiles" : 0,
      "timeUpdatingContentLessIndexes" : 0,
      "timeIndexingWithoutContent" : 0
    }, {
      "providerName" : "org.jetbrains.kotlin.idea.core.script.dependencies.KotlinScriptDependenciesIndexableSetContributor@4aaa6acf",
      "numberOfScannedFiles" : 0,
      "numberOfSkippedFiles" : 0,
      "numberOfFilesForIndexing" : 0,
      "numberOfFilesFullyIndexedByInfrastructureExtensions" : 0,
      "scanningTime" : 0,
      "timeProcessingUpToDateFiles" : 0,
      "timeUpdatingContentLessIndexes" : 0,
      "timeIndexingWithoutContent" : 0
    }, {
      "providerName" : "org.jetbrains.kotlin.idea.core.script.dependencies.KotlinScriptDependenciesIndexableSetContributor@4aaa6acf",
      "numberOfScannedFiles" : 0,
      "numberOfSkippedFiles" : 0,
      "numberOfFilesForIndexing" : 0,
      "numberOfFilesFullyIndexedByInfrastructureExtensions" : 0,
      "scanningTime" : 0,
      "timeProcessingUpToDateFiles" : 0,
      "timeUpdatingContentLessIndexes" : 0,
      "timeIndexingWithoutContent" : 0
    } ],
    "fileProviderStatistics" : [ {
      "providerName" : "Module 'untitled'",
      "totalNumberOfIndexedFiles" : 1,
      "totalNumberOfFilesFullyIndexedByExtensions" : 1,
      "totalIndexingTime" : 66517800,
      "contentLoadingTime" : 3136499,
      "numberOfTooLargeForIndexingFiles" : 0,
      "slowIndexedFiles" : [ ]
    } ]
  }
}